SASOupstox/__init__.py
SASOupstox/upstox.py
aliceblue_fetch_data/__init__.py
aliceblue_fetch_data/alice.py
copytrading_upstox/__init__.py
copytrading_upstox/upstox.py
copytrading_upstox_withoutapi/__init__.py
copytrading_upstox_withoutapi/upstox.py
fyers_withoutapi/__init__.py
fyers_withoutapi/fyers.py
upstox_withoutapi/__init__.py
upstox_withoutapi/upstox.py
zerodha_without_api/__init__.py
zerodha_without_api/zerodha.py
SASOupstox-0.0.1.dist-info/LICENSE
SASOupstox-0.0.1.dist-info/METADATA
SASOupstox-0.0.1.dist-info/WHEEL
SASOupstox-0.0.1.dist-info/top_level.txt
SASOupstox-0.0.1.dist-info/RECORD
